[{"topleft": {"y": 67, "x": 187}, "confidence": 1.0, "bottomright": {"y": 123, "x": 349}, "label": "roll"}, {"topleft": {"y": 158, "x": 173}, "confidence": 1.0, "bottomright": {"y": 217, "x": 260}, "label": "roll"}, {"topleft": {"y": 159, "x": 298}, "confidence": 1.0, "bottomright": {"y": 225, "x": 386}, "label": "roll"}, {"topleft": {"y": 246, "x": 154}, "confidence": 1.0, "bottomright": {"y": 278, "x": 247}, "label": "roll"}, {"topleft": {"y": 244, "x": 273}, "confidence": 1.0, "bottomright": {"y": 293, "x": 318}, "label": "roll"}, {"topleft": {"y": 254, "x": 324}, "confidence": 1.0, "bottomright": {"y": 359, "x": 457}, "label": "roll"}, {"topleft": {"y": 278, "x": 55}, "confidence": 1.0, "bottomright": {"y": 412, "x": 200}, "label": "roll"}, {"topleft": {"y": 239, "x": 168}, "confidence": 1.0, "bottomright": {"y": 378, "x": 322}, "label": "roll"}]